.DS_Store
optilogs/__init__.py
optilogs/config.py
optilogs/logger.py
optilogs-0.1.4.dist-info/METADATA
optilogs-0.1.4.dist-info/WHEEL
optilogs-0.1.4.dist-info/top_level.txt
optilogs-0.1.4.dist-info/RECORD
