Metadata-Version: 2.1
Name: optilogs
Version: 0.1.4
Summary: A simple logging library to send logs to a server
Author: Allan PEREZ GONZALEZ
Author-email: aperezgo74@gmail.com
Classifier: Programming Language :: Python :: 3
Classifier: License :: OSI Approved :: MIT License
Classifier: Operating System :: OS Independent
Requires-Python: >=3.6
Requires-Dist: requests
